Metadata-Version: 2.1
Name: Data-Lake
Version: 0.0.0.1
Summary: processes Datalake to Bronze-Silver_Gold
Home-page: https://upload.pypi.org/legacy/
Author: Imparnert
Author-email: alex-12-04@hotmail.com
License: MIT
Platform: UNKNOWN
Requires-Python: >=3
